fibonacci/__init__.py
ziggy_pydust_template-0.2.0.dist-info/LICENSE
ziggy_pydust_template-0.2.0.dist-info/METADATA
ziggy_pydust_template-0.2.0.dist-info/WHEEL
ziggy_pydust_template-0.2.0.dist-info/RECORD
