Metadata-Version: 2.1
Name: ziggy-pydust-template
Version: 0.2.0
Summary: 
Author: Fulcrum Inc.
Author-email: hello@fulcrum.so
Requires-Python: >=3.11,<4.0
Classifier: Programming Language :: Python :: 3
Classifier: Programming Language :: Python :: 3.11
